{
	"backtrace" : 4,
	"backtraceGraph" : 
	{
		"commands" : 
		[
			"add_custom_target",
			"include",
			"generate_messages",
			"add_dependencies"
		],
		"files" : 
		[
			"/home/alaska/basic_dev/build/airsim_ros/cmake/airsim_ros-genmsg.cmake",
			"/opt/ros/noetic/share/genmsg/cmake/genmsg-extras.cmake",
			"airsim_ros/CMakeLists.txt"
		],
		"nodes" : 
		[
			{
				"file" : 2
			},
			{
				"command" : 2,
				"file" : 2,
				"line" : 86,
				"parent" : 0
			},
			{
				"command" : 1,
				"file" : 1,
				"line" : 307,
				"parent" : 1
			},
			{
				"file" : 0,
				"parent" : 2
			},
			{
				"command" : 0,
				"file" : 0,
				"line" : 909,
				"parent" : 3
			},
			{
				"command" : 3,
				"file" : 0,
				"line" : 950,
				"parent" : 3
			},
			{
				"command" : 3,
				"file" : 0,
				"line" : 948,
				"parent" : 3
			},
			{
				"command" : 3,
				"file" : 0,
				"line" : 946,
				"parent" : 3
			},
			{
				"command" : 3,
				"file" : 0,
				"line" : 944,
				"parent" : 3
			},
			{
				"command" : 3,
				"file" : 0,
				"line" : 942,
				"parent" : 3
			},
			{
				"command" : 3,
				"file" : 0,
				"line" : 936,
				"parent" : 3
			},
			{
				"command" : 3,
				"file" : 0,
				"line" : 932,
				"parent" : 3
			},
			{
				"command" : 3,
				"file" : 0,
				"line" : 934,
				"parent" : 3
			},
			{
				"command" : 3,
				"file" : 0,
				"line" : 928,
				"parent" : 3
			},
			{
				"command" : 3,
				"file" : 0,
				"line" : 918,
				"parent" : 3
			},
			{
				"command" : 3,
				"file" : 0,
				"line" : 920,
				"parent" : 3
			},
			{
				"command" : 3,
				"file" : 0,
				"line" : 930,
				"parent" : 3
			},
			{
				"command" : 3,
				"file" : 0,
				"line" : 1038,
				"parent" : 3
			},
			{
				"command" : 3,
				"file" : 0,
				"line" : 938,
				"parent" : 3
			},
			{
				"command" : 3,
				"file" : 0,
				"line" : 924,
				"parent" : 3
			},
			{
				"command" : 3,
				"file" : 0,
				"line" : 1041,
				"parent" : 3
			},
			{
				"command" : 3,
				"file" : 0,
				"line" : 916,
				"parent" : 3
			},
			{
				"command" : 3,
				"file" : 0,
				"line" : 926,
				"parent" : 3
			},
			{
				"command" : 3,
				"file" : 0,
				"line" : 940,
				"parent" : 3
			},
			{
				"command" : 3,
				"file" : 0,
				"line" : 1044,
				"parent" : 3
			},
			{
				"command" : 3,
				"file" : 0,
				"line" : 922,
				"parent" : 3
			}
		]
	},
	"dependencies" : 
	[
		{
			"backtrace" : 5,
			"id" : "_airsim_ros_generate_messages_check_deps_SetLocalPosition::@2cc5cd2ea28bae4c995f"
		},
		{
			"backtrace" : 6,
			"id" : "_airsim_ros_generate_messages_check_deps_Reset::@2cc5cd2ea28bae4c995f"
		},
		{
			"backtrace" : 7,
			"id" : "_airsim_ros_generate_messages_check_deps_LandGroup::@2cc5cd2ea28bae4c995f"
		},
		{
			"backtrace" : 8,
			"id" : "_airsim_ros_generate_messages_check_deps_Land::@2cc5cd2ea28bae4c995f"
		},
		{
			"backtrace" : 9,
			"id" : "_airsim_ros_generate_messages_check_deps_TakeoffGroup::@2cc5cd2ea28bae4c995f"
		},
		{
			"backtrace" : 10,
			"id" : "_airsim_ros_generate_messages_check_deps_RotorPWM::@2cc5cd2ea28bae4c995f"
		},
		{
			"backtrace" : 11,
			"id" : "_airsim_ros_generate_messages_check_deps_Environment::@2cc5cd2ea28bae4c995f"
		},
		{
			"backtrace" : 12,
			"id" : "_airsim_ros_generate_messages_check_deps_PoseCmd::@2cc5cd2ea28bae4c995f"
		},
		{
			"backtrace" : 13,
			"id" : "_airsim_ros_generate_messages_check_deps_CarState::@2cc5cd2ea28bae4c995f"
		},
		{
			"backtrace" : 14,
			"id" : "_airsim_ros_generate_messages_check_deps_GimbalAngleQuatCmd::@2cc5cd2ea28bae4c995f"
		},
		{
			"backtrace" : 15,
			"id" : "_airsim_ros_generate_messages_check_deps_GPSYaw::@2cc5cd2ea28bae4c995f"
		},
		{
			"backtrace" : 16,
			"id" : "_airsim_ros_generate_messages_check_deps_Altimeter::@2cc5cd2ea28bae4c995f"
		},
		{
			"backtrace" : 17,
			"id" : "std_msgs_generate_messages_py::@2cc5cd2ea28bae4c995f"
		},
		{
			"backtrace" : 18,
			"id" : "_airsim_ros_generate_messages_check_deps_SetGPSPosition::@2cc5cd2ea28bae4c995f"
		},
		{
			"backtrace" : 19,
			"id" : "_airsim_ros_generate_messages_check_deps_VelCmdGroup::@2cc5cd2ea28bae4c995f"
		},
		{
			"backtrace" : 20,
			"id" : "geometry_msgs_generate_messages_py::@2cc5cd2ea28bae4c995f"
		},
		{
			"backtrace" : 21,
			"id" : "_airsim_ros_generate_messages_check_deps_GimbalAngleEulerCmd::@2cc5cd2ea28bae4c995f"
		},
		{
			"backtrace" : 22,
			"id" : "_airsim_ros_generate_messages_check_deps_CarControls::@2cc5cd2ea28bae4c995f"
		},
		{
			"backtrace" : 23,
			"id" : "_airsim_ros_generate_messages_check_deps_Takeoff::@2cc5cd2ea28bae4c995f"
		},
		{
			"backtrace" : 24,
			"id" : "geographic_msgs_generate_messages_py::@2cc5cd2ea28bae4c995f"
		},
		{
			"backtrace" : 25,
			"id" : "_airsim_ros_generate_messages_check_deps_VelCmd::@2cc5cd2ea28bae4c995f"
		}
	],
	"id" : "airsim_ros_generate_messages_py::@2cc5cd2ea28bae4c995f",
	"name" : "airsim_ros_generate_messages_py",
	"paths" : 
	{
		"build" : "airsim_ros",
		"source" : "airsim_ros"
	},
	"sourceGroups" : 
	[
		{
			"name" : "",
			"sourceIndexes" : 
			[
				0
			]
		},
		{
			"name" : "CMake Rules",
			"sourceIndexes" : 
			[
				1,
				2,
				3,
				4,
				5,
				6,
				7,
				8,
				9,
				10,
				11,
				12,
				13,
				14,
				15,
				16,
				17,
				18,
				19,
				20,
				21
			]
		}
	],
	"sources" : 
	[
		{
			"backtrace" : 4,
			"isGenerated" : true,
			"path" : "/home/alaska/basic_dev/build/airsim_ros/CMakeFiles/airsim_ros_generate_messages_py",
			"sourceGroupIndex" : 0
		},
		{
			"backtrace" : 0,
			"isGenerated" : true,
			"path" : "/home/alaska/basic_dev/build/airsim_ros/CMakeFiles/airsim_ros_generate_messages_py.rule",
			"sourceGroupIndex" : 1
		},
		{
			"backtrace" : 0,
			"isGenerated" : true,
			"path" : "/home/alaska/basic_dev/devel/lib/python3/dist-packages/airsim_ros/msg/_GimbalAngleEulerCmd.py.rule",
			"sourceGroupIndex" : 1
		},
		{
			"backtrace" : 0,
			"isGenerated" : true,
			"path" : "/home/alaska/basic_dev/devel/lib/python3/dist-packages/airsim_ros/msg/_GimbalAngleQuatCmd.py.rule",
			"sourceGroupIndex" : 1
		},
		{
			"backtrace" : 0,
			"isGenerated" : true,
			"path" : "/home/alaska/basic_dev/devel/lib/python3/dist-packages/airsim_ros/msg/_GPSYaw.py.rule",
			"sourceGroupIndex" : 1
		},
		{
			"backtrace" : 0,
			"isGenerated" : true,
			"path" : "/home/alaska/basic_dev/devel/lib/python3/dist-packages/airsim_ros/msg/_VelCmd.py.rule",
			"sourceGroupIndex" : 1
		},
		{
			"backtrace" : 0,
			"isGenerated" : true,
			"path" : "/home/alaska/basic_dev/devel/lib/python3/dist-packages/airsim_ros/msg/_VelCmdGroup.py.rule",
			"sourceGroupIndex" : 1
		},
		{
			"backtrace" : 0,
			"isGenerated" : true,
			"path" : "/home/alaska/basic_dev/devel/lib/python3/dist-packages/airsim_ros/msg/_CarControls.py.rule",
			"sourceGroupIndex" : 1
		},
		{
			"backtrace" : 0,
			"isGenerated" : true,
			"path" : "/home/alaska/basic_dev/devel/lib/python3/dist-packages/airsim_ros/msg/_CarState.py.rule",
			"sourceGroupIndex" : 1
		},
		{
			"backtrace" : 0,
			"isGenerated" : true,
			"path" : "/home/alaska/basic_dev/devel/lib/python3/dist-packages/airsim_ros/msg/_Altimeter.py.rule",
			"sourceGroupIndex" : 1
		},
		{
			"backtrace" : 0,
			"isGenerated" : true,
			"path" : "/home/alaska/basic_dev/devel/lib/python3/dist-packages/airsim_ros/msg/_Environment.py.rule",
			"sourceGroupIndex" : 1
		},
		{
			"backtrace" : 0,
			"isGenerated" : true,
			"path" : "/home/alaska/basic_dev/devel/lib/python3/dist-packages/airsim_ros/msg/_PoseCmd.py.rule",
			"sourceGroupIndex" : 1
		},
		{
			"backtrace" : 0,
			"isGenerated" : true,
			"path" : "/home/alaska/basic_dev/devel/lib/python3/dist-packages/airsim_ros/msg/_RotorPWM.py.rule",
			"sourceGroupIndex" : 1
		},
		{
			"backtrace" : 0,
			"isGenerated" : true,
			"path" : "/home/alaska/basic_dev/devel/lib/python3/dist-packages/airsim_ros/srv/_SetGPSPosition.py.rule",
			"sourceGroupIndex" : 1
		},
		{
			"backtrace" : 0,
			"isGenerated" : true,
			"path" : "/home/alaska/basic_dev/devel/lib/python3/dist-packages/airsim_ros/srv/_Takeoff.py.rule",
			"sourceGroupIndex" : 1
		},
		{
			"backtrace" : 0,
			"isGenerated" : true,
			"path" : "/home/alaska/basic_dev/devel/lib/python3/dist-packages/airsim_ros/srv/_TakeoffGroup.py.rule",
			"sourceGroupIndex" : 1
		},
		{
			"backtrace" : 0,
			"isGenerated" : true,
			"path" : "/home/alaska/basic_dev/devel/lib/python3/dist-packages/airsim_ros/srv/_Land.py.rule",
			"sourceGroupIndex" : 1
		},
		{
			"backtrace" : 0,
			"isGenerated" : true,
			"path" : "/home/alaska/basic_dev/devel/lib/python3/dist-packages/airsim_ros/srv/_LandGroup.py.rule",
			"sourceGroupIndex" : 1
		},
		{
			"backtrace" : 0,
			"isGenerated" : true,
			"path" : "/home/alaska/basic_dev/devel/lib/python3/dist-packages/airsim_ros/srv/_Reset.py.rule",
			"sourceGroupIndex" : 1
		},
		{
			"backtrace" : 0,
			"isGenerated" : true,
			"path" : "/home/alaska/basic_dev/devel/lib/python3/dist-packages/airsim_ros/srv/_SetLocalPosition.py.rule",
			"sourceGroupIndex" : 1
		},
		{
			"backtrace" : 0,
			"isGenerated" : true,
			"path" : "/home/alaska/basic_dev/devel/lib/python3/dist-packages/airsim_ros/msg/__init__.py.rule",
			"sourceGroupIndex" : 1
		},
		{
			"backtrace" : 0,
			"isGenerated" : true,
			"path" : "/home/alaska/basic_dev/devel/lib/python3/dist-packages/airsim_ros/srv/__init__.py.rule",
			"sourceGroupIndex" : 1
		}
	],
	"type" : "UTILITY"
}
